edx_submissions-3.12.1.dist-info/licenses/LICENSE.txt
submissions/__init__.py
submissions/admin.py
submissions/api.py
submissions/errors.py
submissions/models.py
submissions/permissions.py
submissions/serializers.py
submissions/team_api.py
submissions/urls.py
submissions/management/__init__.py
submissions/management/commands/__init__.py
submissions/management/commands/analyze_uploaded_file_sizes.py
submissions/management/commands/update_submissions_uuids.py
submissions/migrations/0001_initial.py
submissions/migrations/0001_squashed_0005_CreateTeamModel.py
submissions/migrations/0002_auto_20151119_0913.py
submissions/migrations/0002_team_submission_optional.py
submissions/migrations/0003_ensure_ascii.py
submissions/migrations/0003_submission_status.py
submissions/migrations/0004_externalgraderdetail.py
submissions/migrations/0004_remove_django_extensions.py
submissions/migrations/0005_CreateTeamModel.py
submissions/migrations/0005_submissionfile.py
submissions/migrations/0006_mariadb_uuid_conversion.py
submissions/migrations/0007_merge_20251020_2045.py
submissions/migrations/__init__.py
submissions/views/__init__.py
submissions/views/xqueue.py
edx_submissions-3.12.1.dist-info/METADATA
edx_submissions-3.12.1.dist-info/WHEEL
edx_submissions-3.12.1.dist-info/top_level.txt
edx_submissions-3.12.1.dist-info/RECORD
